opencensus/__init__.py
opencensus/common/__init__.py
opencensus/common/runtime_context/__init__.py
opencensus/common/runtime_context/version.py
opencensus_context-0.1.3.dist-info/METADATA
opencensus_context-0.1.3.dist-info/WHEEL
opencensus_context-0.1.3.dist-info/namespace_packages.txt
opencensus_context-0.1.3.dist-info/top_level.txt
opencensus_context-0.1.3.dist-info/RECORD
